{
  "id": 34613906,
  "play_path_64": "http://audio.cos.xmcdn.com/group26/M06/32/81/wKgJRljk-n3yBvbpAQozaDMji98193.m4a",
  "play_path_32": "http://audio.cos.xmcdn.com/group26/M0B/33/AC/wKgJRljlCTbgrEzJAGXIXeO8HGM463.m4a",
  "play_path": "http://audio.cos.xmcdn.com/group26/M06/32/81/wKgJRljk-n3yBvbpAQozaDMji98193.m4a",
  "duration": 2154,
  "title": "421世界科学中心转移【法国】",
  "nickname": null,
  "uid": 32231821,
  "waveform": "group26/M01/32/90/wKgJRljk-ybjp-97AAAKyLZMVoc4730.js",
  "upload_id": "u_35348810",
  "cover_url": "https://imagev2.xmcdn.com/group27/M05/2D/EF/wKgJW1jk-CzzpYngAAAKytDNVHc634.jpg!op_type=5&upload_type=album&device_type=ios&name=web_large&strip=0&quality=7",
  "cover_url_142": "https://imagev2.xmcdn.com/group27/M05/2D/EF/wKgJW1jk-CzzpYngAAAKytDNVHc634.jpg!op_type=5&upload_type=album&device_type=ios&name=web_large&strip=0&quality=7",
  "formatted_created_at": "2017-04-05 22:08:00",
  "is_favorited": false,
  "play_count": 7810,
  "comments_count": 11,
  "shares_count": 11,
  "favorites_count": 31,
  "album_id": 4769101,
  "album_title": "思考盒子",
  "intro": "外表的美只能取悦于人的眼睛，而内在的美却能感染人的灵魂。\r\n\r\n\r\n  \r\n \r\n \r\n \r\n\r\n\r\n\r\n ——伏尔泰",
  "have_more_intro": false,
  "time_until_now": "3年前",
  "category_name": null,
  "category_title": null,
  "played_secs": null,
  "is_paid": false,
  "is_free": false,
  "price": null,
  "discounted_price": null
}