{
  "id": 22503448,
  "play_path_64": "http://audio.cos.xmcdn.com/group17/M04/4A/6A/wKgJJFfv8emjywPoALTGA0KJlec535.m4a",
  "play_path_32": "http://audio.cos.xmcdn.com/group20/M05/48/D1/wKgJLFfv8dDASCwhAEUff1eMQzM065.m4a",
  "play_path": "http://audio.cos.xmcdn.com/group17/M04/4A/6A/wKgJJFfv8emjywPoALTGA0KJlec535.m4a",
  "duration": 1463,
  "title": "物种起源—前传：01. 教皇Hold不住",
  "nickname": null,
  "uid": 10946830,
  "waveform": "group17/M04/4A/BF/wKgJKVfv8evCFJRbAAAKwG0irmU3405.js",
  "upload_id": "u_22497105",
  "cover_url": "https://imagev2.xmcdn.com/group20/M00/4A/A3/wKgJJ1fv8ovQShx8AAFaA0vtrTk666.jpg!op_type=5&upload_type=album&device_type=ios&name=web_large&strip=0&quality=7",
  "cover_url_142": "https://imagev2.xmcdn.com/group20/M00/4A/A3/wKgJJ1fv8ovQShx8AAFaA0vtrTk666.jpg!op_type=5&upload_type=album&device_type=ios&name=web_large&strip=0&quality=7",
  "formatted_created_at": "2016-10-02 01:29:00",
  "is_favorited": false,
  "play_count": 271472,
  "comments_count": 301,
  "shares_count": 541,
  "favorites_count": 1508,
  "album_id": 5411224,
  "album_title": "科学史评话最新专辑",
  "intro": "",
  "have_more_intro": false,
  "time_until_now": "3年前",
  "category_name": null,
  "category_title": null,
  "played_secs": null,
  "is_paid": false,
  "is_free": false,
  "price": null,
  "discounted_price": null
}