{
  "id": 296732025,
  "play_path_64": "http://aod.cos.tx.xmcdn.com/group81/M02/1D/4A/wKgPEl6-dtmQ62PJAK6PpbArew8233.m4a",
  "play_path_32": "http://aod.cos.tx.xmcdn.com/group79/M08/12/61/wKgPC16-dtSTNHymAEK-vYVELs8189.m4a",
  "play_path": "http://aod.cos.tx.xmcdn.com/group81/M02/1D/4A/wKgPEl6-dtmQ62PJAK6PpbArew8233.m4a",
  "duration": 1412,
  "title": "批三国",
  "nickname": null,
  "uid": 158802478,
  "waveform": "group79/M0B/12/60/wKgPC16-dsGT1HlOAAAK2cKt2rA7321.js",
  "upload_id": "u_6566246500",
  "cover_url": "https://imagev2.xmcdn.com/group81/M01/17/E6/wKgPDV6-dWDzSwnUAAB0MJwuK0I419.jpg!op_type=5&upload_type=album&device_type=ios&name=web_large&strip=0&quality=7",
  "cover_url_142": "https://imagev2.xmcdn.com/group81/M01/17/E6/wKgPDV6-dWDzSwnUAAB0MJwuK0I419.jpg!op_type=5&upload_type=album&device_type=ios&name=web_large&strip=0&quality=7",
  "formatted_created_at": "2020-05-15 19:02:00",
  "is_favorited": false,
  "play_count": 763,
  "comments_count": 0,
  "shares_count": 0,
  "favorites_count": 4,
  "album_id": 37999456,
  "album_title": "苏文茂表演相声集",
  "intro": "",
  "have_more_intro": false,
  "time_until_now": "17天前",
  "category_name": null,
  "category_title": null,
  "played_secs": null,
  "is_paid": false,
  "is_free": false,
  "price": null,
  "discounted_price": null
}