{
  "id": 33609955,
  "play_path_64": "http://aod.cos.tx.xmcdn.com/group27/M04/9B/61/wKgJR1jWcOTSzS6bAiUGDdop5Zc528.m4a",
  "play_path_32": "http://aod.cos.tx.xmcdn.com/group27/M05/9B/86/wKgJW1jWc7zjL5O7ANHpBB-1Hq8412.m4a",
  "play_path": "http://aod.cos.tx.xmcdn.com/group27/M04/9B/61/wKgJR1jWcOTSzS6bAiUGDdop5Zc528.m4a",
  "duration": 4444,
  "title": "397生物圈大事件【寒武纪生命大爆发】",
  "nickname": null,
  "uid": 32231821,
  "waveform": "group27/M07/9B/49/wKgJW1jWcOqBOcdjAAAKxPuo0gw6909.js",
  "upload_id": "u_34336377",
  "cover_url": "https://imagev2.xmcdn.com/group27/M06/9A/F7/wKgJR1jWa9bCQHtlAAFPKSkSJ5E695.jpg!op_type=5&upload_type=album&device_type=ios&name=web_large&strip=0&quality=7",
  "cover_url_142": "https://imagev2.xmcdn.com/group27/M06/9A/F7/wKgJR1jWa9bCQHtlAAFPKSkSJ5E695.jpg!op_type=5&upload_type=album&device_type=ios&name=web_large&strip=0&quality=7",
  "formatted_created_at": "2017-03-25 21:28:00",
  "is_favorited": false,
  "play_count": 16793,
  "comments_count": 37,
  "shares_count": 11,
  "favorites_count": 75,
  "album_id": 4769101,
  "album_title": "思考盒子",
  "intro": "故事从一双玻璃鞋开始\r\n\r\n\r\n 最初灰姑娘还没有回忆\r\n\r\n\r\n 不懂小王子有多美丽\r\n\r\n\r\n 直到伊甸园长出第一颗菩提\r\n\r\n\r\n 我们才学会孤寂\r\n\r\n\r\n 在天鹅湖中边走边寻觅寻觅\r\n\r\n\r\n 最后每个人都有个结局\r\n\r\n\r\n 只是踏跛了玻璃鞋之后\r\n\r\n\r\n 你的小王子跑到哪里\r\n\r\n\r\n 蝴蝶的玫瑰可能依然留在\r\n\r\n\r\n 几亿年前的寒武纪\r\n\r\n\r\n 怕镜花水月终于来不及\r\n\r\n\r\n 去相遇",
  "have_more_intro": false,
  "time_until_now": "3年前",
  "category_name": null,
  "category_title": null,
  "played_secs": null,
  "is_paid": false,
  "is_free": false,
  "price": null,
  "discounted_price": null
}