{
  "id": 18595359,
  "play_path_64": "http://audio.cos.xmcdn.com/group17/M09/31/5B/wKgJJFeLq9WiGqlTACy9Icm6mdE105.m4a",
  "play_path_32": "http://audio.cos.xmcdn.com/group20/M08/31/81/wKgJLFeLw5WQUf2_ABEdzAzfKf4583.m4a",
  "play_path": "http://audio.cos.xmcdn.com/group17/M09/31/5B/wKgJJFeLq9WiGqlTACy9Icm6mdE105.m4a",
  "duration": 361,
  "title": "【未来预言】脑机接口",
  "nickname": null,
  "uid": 43396178,
  "waveform": "group17/M09/31/89/wKgJKVeLq9HSUJ1fAAALrOxisu00039.js",
  "upload_id": "u_18273525",
  "cover_url": "https://imagev2.xmcdn.com/group19/M02/31/5F/wKgJK1eLq66wNf_9AABun_KNt90281.jpg!op_type=5&upload_type=album&device_type=ios&name=web_large&strip=0&quality=7",
  "cover_url_142": "https://imagev2.xmcdn.com/group19/M02/31/5F/wKgJK1eLq66wNf_9AABun_KNt90281.jpg!op_type=5&upload_type=album&device_type=ios&name=web_large&strip=0&quality=7",
  "formatted_created_at": "2016-07-18 00:02:00",
  "is_favorited": false,
  "play_count": 32773,
  "comments_count": 7,
  "shares_count": 2,
  "favorites_count": 45,
  "album_id": 4310827,
  "album_title": "回到2049",
  "intro": "人类的大脑终将与机器相连接，脑机互联会对世界产生什么样的影响，前进的道路上又有什么难以逾越的屏障？",
  "have_more_intro": false,
  "time_until_now": "3年前",
  "category_name": null,
  "category_title": null,
  "played_secs": null,
  "is_paid": false,
  "is_free": false,
  "price": null,
  "discounted_price": null
}