{
  "id": 18839768,
  "play_path_64": "http://aod.cos.tx.xmcdn.com/group17/M04/3E/B0/wKgJKVeQgvWhNgwoAWEBOVrWDTc673.m4a",
  "play_path_32": "http://aod.cos.tx.xmcdn.com/group17/M04/3E/AE/wKgJKVeQgt2jzVvYAIb4G3wCgVY803.m4a",
  "play_path": "http://aod.cos.tx.xmcdn.com/group17/M04/3E/B0/wKgJKVeQgvWhNgwoAWEBOVrWDTc673.m4a",
  "duration": 2857,
  "title": "122：蜂王传",
  "nickname": null,
  "uid": 7200706,
  "waveform": "group17/M06/3E/74/wKgJJFeQgu7A3d7WAAAKyv9RsrY5665.js",
  "upload_id": "u_18475882",
  "cover_url": "https://imagev2.xmcdn.com/group13/M09/37/1E/wKgDXVWWXQ2D0qUfAAM0Is5jf_s669.jpg!op_type=5&upload_type=album&device_type=ios&name=web_large&strip=0&quality=7",
  "cover_url_142": "https://imagev2.xmcdn.com/group13/M09/37/1E/wKgDXVWWXQ2D0qUfAAM0Is5jf_s669.jpg!op_type=5&upload_type=album&device_type=ios&name=web_large&strip=0&quality=7",
  "formatted_created_at": "2016-07-22 18:00:00",
  "is_favorited": false,
  "play_count": 414443,
  "comments_count": 226,
  "shares_count": 159,
  "favorites_count": 424,
  "album_id": 246622,
  "album_title": "原来是这样？！",
  "intro": "继去年推出昆虫宫斗大戏《蚁后传》之后，“原样”在2016年中再推“姊妹篇”大制作《蜂王传》！蜜蜂的蜂王是如何产生的？蜂王浆又是什么东西？在登上权力巅峰之前，蜂王需要克服哪些困难？为什么雄蜂在交配后也会死去？工蜂的劳碌一生又是如何度过的？这一次，我们将跟随蜂王“月儿”，了解蜂王的一生，并走进蜜蜂的王国。",
  "have_more_intro": false,
  "time_until_now": "3年前",
  "category_name": null,
  "category_title": null,
  "played_secs": null,
  "is_paid": false,
  "is_free": false,
  "price": null,
  "discounted_price": null
}