{
  "id": 62834349,
  "play_path_64": "http://audio.cos.xmcdn.com/group36/M08/99/CF/wKgJUlo0wbSRNOboAWNRA5QLCR0853.m4a",
  "play_path_32": "http://audio.cos.xmcdn.com/group37/M01/72/B2/wKgJoFo0wezyo4cMAIfaXC4ymvc965.m4a",
  "play_path": "http://audio.cos.xmcdn.com/group36/M08/99/CF/wKgJUlo0wbSRNOboAWNRA5QLCR0853.m4a",
  "duration": 2876,
  "title": "1019中古世界奇迹【亚历山大陵墓】",
  "nickname": null,
  "uid": 32231821,
  "waveform": "group36/M09/99/F8/wKgJUlo0wjqiS20VAAAKeEGOvt07308.js",
  "upload_id": "u_64897949",
  "cover_url": "https://imagev2.xmcdn.com/group36/M0B/99/5D/wKgJUlo0v1GjRuzKAAD6C6cXMX8788.jpg!op_type=5&upload_type=album&device_type=ios&name=web_large&strip=0&quality=7",
  "cover_url_142": "https://imagev2.xmcdn.com/group36/M0B/99/5D/wKgJUlo0v1GjRuzKAAD6C6cXMX8788.jpg!op_type=5&upload_type=album&device_type=ios&name=web_large&strip=0&quality=7",
  "formatted_created_at": "2017-12-16 14:47:00",
  "is_favorited": false,
  "play_count": 17868,
  "comments_count": 35,
  "shares_count": 11,
  "favorites_count": 61,
  "album_id": 4769101,
  "album_title": "思考盒子",
  "intro": "思考盒子官方微信群已经成立，微信搜索思考盒子的全拼【sikaohezi】，加我的个人微信，我给你拉进来，赶紧来吧！\r\n \r\n \r\n 官方QQ群也已经开放，QQ群号码【30024640】 新浪微博也叫【思考盒子】\r\n \r\n \r\n  \r\n \r\n \r\n 2017圣诞特别节目预热中，2017年12月24日，将播出思考盒子圣诞特别节目，欢迎留言，提问，我将在节目中选读留言，回答各种各样的奇葩问题。可以通过喜马拉雅私信，或者我的微信，或者在本期节目中留言。",
  "have_more_intro": false,
  "time_until_now": "2年前",
  "category_name": null,
  "category_title": null,
  "played_secs": null,
  "is_paid": false,
  "is_free": false,
  "price": null,
  "discounted_price": null
}