{
  "id": 216032380,
  "play_path_64": "http://aod.cos.tx.xmcdn.com/group64/M04/E4/AE/wKgMaV2Q4EuBY8g-AEPnse93VxE896.m4a",
  "play_path_32": "http://aod.cos.tx.xmcdn.com/group64/M04/E4/AE/wKgMaV2Q4E7iL5JiABn5DMb1Vcg567.m4a",
  "play_path": "http://aod.cos.tx.xmcdn.com/group64/M04/E4/AE/wKgMaV2Q4EuBY8g-AEPnse93VxE896.m4a",
  "duration": 549,
  "title": "语音时代：塑造时代的强大推手",
  "nickname": null,
  "uid": 43396178,
  "waveform": "group64/M04/E4/B0/wKgMc12Q4E6SsUANAAAKWUUdclE6926.js",
  "upload_id": "u_240666994",
  "cover_url": "https://imagev2.xmcdn.com/group64/M04/E4/AE/wKgMc12Q4DOhF13QAAMNeOUP6Z4634.jpg!op_type=5&upload_type=album&device_type=ios&name=web_large&strip=0&quality=7",
  "cover_url_142": "https://imagev2.xmcdn.com/group64/M04/E4/AE/wKgMc12Q4DOhF13QAAMNeOUP6Z4634.jpg!op_type=5&upload_type=album&device_type=ios&name=web_large&strip=0&quality=7",
  "formatted_created_at": "2019-09-30 00:48:00",
  "is_favorited": false,
  "play_count": 22510,
  "comments_count": 19,
  "shares_count": 12,
  "favorites_count": 57,
  "album_id": 4310827,
  "album_title": "回到2049",
  "intro": "智能语音正在以及将会对世界产生怎样改变？\r\n \r\n \r\n \r\n \r\n 节目文本、视频，及更多精神与物质上的享受，尽在公众号“回到2049”。",
  "have_more_intro": false,
  "time_until_now": "7月前",
  "category_name": null,
  "category_title": null,
  "played_secs": null,
  "is_paid": false,
  "is_free": false,
  "price": null,
  "discounted_price": null
}