{"id":259480458,"play_path_64":"http://audio.cos.xmcdn.com/group75/M03/E6/5F/wKgO015V_P-g5wM_APEMGpn81zI931.m4a","play_path_32":"http://audio.cos.xmcdn.com/group75/M03/E6/5F/wKgO015V_P7x_Hc1AF27IAHIg_U005.m4a","play_path":"http://audio.cos.xmcdn.com/group75/M03/E6/5F/wKgO015V_P-g5wM_APEMGpn81zI931.m4a","duration":1930,"title":"宇宙速度有上限，这事真的很奇怪","nickname":null,"uid":21189289,"waveform":"group76/M09/E1/F8/wKgO3l5V_OHD1IB5AAAKyNMFng01533.js","upload_id":"u_6108218980","cover_url":"https://imagev2.xmcdn.com/group55/M01/91/3C/wKgLdVxw7KTgn7vcAAFf2rzyUUA124.jpg!op_type=5&upload_type=album&device_type=ios&name=web_large&strip=0&quality=7","cover_url_142":"https://imagev2.xmcdn.com/group55/M01/91/3C/wKgLdVxw7KTgn7vcAAFf2rzyUUA124.jpg!op_type=5&upload_type=album&device_type=ios&name=web_large&strip=0&quality=7","formatted_created_at":"2020-02-26 13:06:00","is_favorited":false,"play_count":9644,"comments_count":38,"shares_count":4,"favorites_count":52,"album_id":21469108,"album_title":"科学星球","intro":"光速到底是怎么回事，光速不变会推出什么奇怪的结论？","have_more_intro":false,"time_until_now":"2月前","category_name":null,"category_title":null,"played_secs":null,"is_paid":false,"is_free":false,"price":null,"discounted_price":null}