{
  "id": 18400772,
  "play_path_64": "http://aod.cos.tx.xmcdn.com/group19/M08/23/78/wKgJK1eGaOjSaPgPACV9Idngcvs027.m4a",
  "play_path_32": "http://aod.cos.tx.xmcdn.com/group20/M06/23/C5/wKgJLFeGwT-SyXV1AA5YWNIAYJY250.m4a",
  "play_path": "http://aod.cos.tx.xmcdn.com/group19/M08/23/78/wKgJK1eGaOjSaPgPACV9Idngcvs027.m4a",
  "duration": 303,
  "title": "【未来预言】远程医疗监控",
  "nickname": null,
  "uid": 43396178,
  "waveform": "group19/M08/23/81/wKgJJleGaOnik_BeAAALO2Qpbuw4430.js",
  "upload_id": "u_18024317",
  "cover_url": "https://imagev2.xmcdn.com/group17/M05/23/5B/wKgJKVeGaNKwWDk1AADHEafVCF8970.jpg!op_type=5&upload_type=album&device_type=ios&name=web_large&strip=0&quality=7",
  "cover_url_142": "https://imagev2.xmcdn.com/group17/M05/23/5B/wKgJKVeGaNKwWDk1AADHEafVCF8970.jpg!op_type=5&upload_type=album&device_type=ios&name=web_large&strip=0&quality=7",
  "formatted_created_at": "2016-07-14 00:14:00",
  "is_favorited": false,
  "play_count": 31608,
  "comments_count": 6,
  "shares_count": 7,
  "favorites_count": 37,
  "album_id": 4310827,
  "album_title": "回到2049",
  "intro": "未来时代的医疗革命。",
  "have_more_intro": false,
  "time_until_now": "3年前",
  "category_name": null,
  "category_title": null,
  "played_secs": null,
  "is_paid": false,
  "is_free": false,
  "price": null,
  "discounted_price": null
}