{
  "id": 46106366,
  "play_path_64": "http://audio.cos.xmcdn.com/group30/M0A/67/7D/wKgJXlmC6IezkkkgAHUWQvfGQ68871.m4a",
  "play_path_32": "http://audio.cos.xmcdn.com/group30/M0A/67/7F/wKgJXlmC6InQeq40ACyyUV7Vu_c512.m4a",
  "play_path": "http://audio.cos.xmcdn.com/group30/M0A/67/7D/wKgJXlmC6IezkkkgAHUWQvfGQ68871.m4a",
  "duration": 948,
  "title": "《红花绿叶》郭德纲 于谦",
  "nickname": null,
  "uid": 1000202,
  "waveform": "group30/M0A/66/C5/wKgJXlmC4-TgnWdwAAAImkJXuWg9726.js",
  "upload_id": "c_804780",
  "cover_url": "https://imagev2.xmcdn.com/group31/M07/0E/5B/wKgJX1mAQg2SWaYDAAAw0CICWi8444.jpg!op_type=5&upload_type=album&device_type=ios&name=web_large&strip=0&quality=7",
  "cover_url_142": "https://imagev2.xmcdn.com/group31/M07/0E/5B/wKgJX1mAQg2SWaYDAAAw0CICWi8444.jpg!op_type=5&upload_type=album&device_type=ios&name=web_large&strip=0&quality=7",
  "formatted_created_at": "2017-08-03 17:10:00",
  "is_favorited": false,
  "play_count": 6664527,
  "comments_count": 332,
  "shares_count": 602,
  "favorites_count": 6594,
  "album_id": 9723091,
  "album_title": "郭德纲21年相声精选",
  "intro": "",
  "have_more_intro": false,
  "time_until_now": "2年前",
  "category_name": null,
  "category_title": null,
  "played_secs": null,
  "is_paid": false,
  "is_free": false,
  "price": null,
  "discounted_price": null
}