{
  "id": 37142754,
  "play_path_64": "http://aod.cos.tx.xmcdn.com/group27/M04/06/FA/wKgJR1kL4FPgEgJLAPG5lw3TNdo590.m4a",
  "play_path_32": "http://aod.cos.tx.xmcdn.com/group26/M06/0A/A6/wKgJRlkL4C3R_43lAFxs2Nmwqj4950.m4a",
  "play_path": "http://aod.cos.tx.xmcdn.com/group27/M04/06/FA/wKgJR1kL4FPgEgJLAPG5lw3TNdo590.m4a",
  "duration": 1956,
  "title": "S01E20薛定谔的猫：论量子与表象的世界",
  "nickname": null,
  "uid": 43396178,
  "waveform": "group27/M08/06/FA/wKgJR1kL4FiiAsP6AAANqinPKKM4705.js",
  "upload_id": "u_37966918",
  "cover_url": "https://imagev2.xmcdn.com/group27/M08/07/09/wKgJW1kL3oSzUL2XAABFUNf6ous987.jpg!op_type=5&upload_type=album&device_type=ios&name=web_large&strip=0&quality=7",
  "cover_url_142": "https://imagev2.xmcdn.com/group27/M08/07/09/wKgJW1kL3oSzUL2XAABFUNf6ous987.jpg!op_type=5&upload_type=album&device_type=ios&name=web_large&strip=0&quality=7",
  "formatted_created_at": "2017-05-05 18:00:00",
  "is_favorited": false,
  "play_count": 19707,
  "comments_count": 22,
  "shares_count": 12,
  "favorites_count": 76,
  "album_id": 4310827,
  "album_title": "回到2049",
  "intro": "薛定谔的猫让我们一窥诡异的量子世界，如此诡异的量子世界为什么会构成我们看似稳定的实体世界，猫可能是既死又活的吗？这是一场随机与稳定的较量，一次微观与宏观的博弈，一个虚幻与现实的故事，这不仅仅是物理，更是哲学、逻辑与形而上的头脑风暴。",
  "have_more_intro": false,
  "time_until_now": "3年前",
  "category_name": null,
  "category_title": null,
  "played_secs": null,
  "is_paid": false,
  "is_free": false,
  "price": null,
  "discounted_price": null
}