{
  "id": 282788877,
  "play_path_64": "http://aod.cos.tx.xmcdn.com/group75/M04/B9/9B/wKgO016UjZeiwIX0AjheuRTqgAw701.m4a",
  "play_path_32": "http://aod.cos.tx.xmcdn.com/group74/M04/AF/0F/wKgO3F6UlAyh4V2UANz7qJD2VfM606.m4a",
  "play_path": "http://aod.cos.tx.xmcdn.com/group75/M04/B9/9B/wKgO016UjZeiwIX0AjheuRTqgAw701.m4a",
  "duration": 4553,
  "title": "2138【番外篇】闲聊70多分钟",
  "nickname": null,
  "uid": 32231821,
  "waveform": "group76/M03/C7/17/wKgO1F6Uk6KzBm3AAAAKiH1L8Ck1058.js",
  "upload_id": "u_6299029780",
  "cover_url": "https://imagev2.xmcdn.com/group78/M01/F1/7F/wKgO1l6H4e2hUbPlAAB3XDpOf6o336.jpg!op_type=5&upload_type=album&device_type=ios&name=web_large&strip=0&quality=7",
  "cover_url_142": "https://imagev2.xmcdn.com/group78/M01/F1/7F/wKgO1l6H4e2hUbPlAAB3XDpOf6o336.jpg!op_type=5&upload_type=album&device_type=ios&name=web_large&strip=0&quality=7",
  "formatted_created_at": "2020-04-14 00:01:00",
  "is_favorited": false,
  "play_count": 17736,
  "comments_count": 81,
  "shares_count": 5,
  "favorites_count": 129,
  "album_id": 4769101,
  "album_title": "思考盒子",
  "intro": "拼命探索,不计后果！我讲的内容99%是从网上抄来的，1%是我自己瞎编的。与科学一毛钱关系也没有，千万别当真！千万别当真！千万别当真！",
  "have_more_intro": false,
  "time_until_now": "25天前",
  "category_name": null,
  "category_title": null,
  "played_secs": null,
  "is_paid": false,
  "is_free": false,
  "price": null,
  "discounted_price": null
}