{
  "id": 150823953,
  "play_path_64": "http://aod.cos.tx.xmcdn.com/group52/M01/81/2F/wKgLcFwy9_Xjb4iKAEtoVp58qYY497.m4a",
  "play_path_32": "http://aod.cos.tx.xmcdn.com/group52/M01/81/2F/wKgLcFwy9_PAd4omABzW6P1VK1E641.m4a",
  "play_path": "http://aod.cos.tx.xmcdn.com/group52/M01/81/2F/wKgLcFwy9_Xjb4iKAEtoVp58qYY497.m4a",
  "duration": 610,
  "title": "河流为什么都是弯的？蛇的形状有什么科学？生活中常见的弹性曲线",
  "nickname": null,
  "uid": 125447116,
  "waveform": "group52/M01/81/32/wKgLcFwy9_6hsBUaAAALLuLDoWs2434.js",
  "upload_id": "u_163834351",
  "cover_url": "https://imagev2.xmcdn.com/group54/M00/7D/76/wKgLfVwy4KvDr_FoAAFfgYGiXlM866.jpg!op_type=5&upload_type=album&device_type=ios&name=web_large&strip=0&quality=7",
  "cover_url_142": "https://imagev2.xmcdn.com/group54/M00/7D/76/wKgLfVwy4KvDr_FoAAFfgYGiXlM866.jpg!op_type=5&upload_type=album&device_type=ios&name=web_large&strip=0&quality=7",
  "formatted_created_at": "2019-01-07 14:57:00",
  "is_favorited": false,
  "play_count": 18983,
  "comments_count": 4,
  "shares_count": 10,
  "favorites_count": 42,
  "album_id": 20486769,
  "album_title": "理工男有话说",
  "intro": "自然科学短视频新媒体，有理、有趣、有节操。",
  "have_more_intro": false,
  "time_until_now": "1年前",
  "category_name": null,
  "category_title": null,
  "played_secs": null,
  "is_paid": false,
  "is_free": false,
  "price": null,
  "discounted_price": null
}