{
  "id": 53584822,
  "play_path_64": "http://aod.cos.tx.xmcdn.com/group34/M06/51/58/wKgJYVnZM-ihtYYdAAouxPi7rww551.m4a",
  "play_path_32": "http://aod.cos.tx.xmcdn.com/group34/M06/51/58/wKgJYVnZM-iCesETAAPnLVRDG5w433.m4a",
  "play_path": "http://aod.cos.tx.xmcdn.com/group34/M06/51/58/wKgJYVnZM-ihtYYdAAouxPi7rww551.m4a",
  "duration": 82,
  "title": "《科学史评话》诚邀知识后援团",
  "nickname": null,
  "uid": 10946830,
  "waveform": "group34/M06/51/58/wKgJYVnZM-jDTMj2AAAIj34-M1o5357.js",
  "upload_id": "u_55250608",
  "cover_url": "https://imagev2.xmcdn.com/group33/M04/B3/CC/wKgJTFmh5yrzE0ttAAB73SAsKmg207.jpg!op_type=5&upload_type=album&device_type=ios&name=web_large&strip=0&quality=7",
  "cover_url_142": "https://imagev2.xmcdn.com/group33/M04/B3/CC/wKgJTFmh5yrzE0ttAAB73SAsKmg207.jpg!op_type=5&upload_type=album&device_type=ios&name=web_large&strip=0&quality=7",
  "formatted_created_at": "2017-10-08 04:07:00",
  "is_favorited": false,
  "play_count": 64025,
  "comments_count": 3,
  "shares_count": 1,
  "favorites_count": 36,
  "album_id": 5411224,
  "album_title": "科学史评话最新专辑",
  "intro": "科学史评话最新专辑",
  "have_more_intro": false,
  "time_until_now": "2年前",
  "category_name": null,
  "category_title": null,
  "played_secs": null,
  "is_paid": false,
  "is_free": false,
  "price": null,
  "discounted_price": null
}