{
  "id": 265159481,
  "play_path_64": "http://aod.cos.tx.xmcdn.com/group76/M02/CF/4C/wKgO1F5lFyLQ112rAGebKzePRoM897.m4a",
  "play_path_32": "http://aod.cos.tx.xmcdn.com/group76/M02/CF/05/wKgO3l5lFzGg2ExfAChOMYl1UCs959.m4a",
  "play_path": "http://aod.cos.tx.xmcdn.com/group76/M02/CF/4C/wKgO1F5lFyLQ112rAGebKzePRoM897.m4a",
  "duration": 829,
  "title": "阿西莫夫与时间旅行",
  "nickname": null,
  "uid": 43396178,
  "waveform": "group76/M02/CF/4D/wKgO1F5lFySTWJFnAAAKW-TNn1s6270.js",
  "upload_id": "u_6148469600",
  "cover_url": "https://imagev2.xmcdn.com/group75/M00/C3/B3/wKgO3V5k2tbx7NekAACwqmKfWqE257.jpg!op_type=5&upload_type=album&device_type=ios&name=web_large&strip=0&quality=7",
  "cover_url_142": "https://imagev2.xmcdn.com/group75/M00/C3/B3/wKgO3V5k2tbx7NekAACwqmKfWqE257.jpg!op_type=5&upload_type=album&device_type=ios&name=web_large&strip=0&quality=7",
  "formatted_created_at": "2020-03-09 00:01:00",
  "is_favorited": false,
  "play_count": 23054,
  "comments_count": 42,
  "shares_count": 2,
  "favorites_count": 89,
  "album_id": 4310827,
  "album_title": "回到2049",
  "intro": "历史自然演进与修正历史以创造一个美好的现实，该如何选择？\r\n\r\n\r\n \r\n  \r\n \r\n \r\n  \r\n \r\n \r\n \r\n 节目文本、视频，及更多精神与物质上的享受，尽在公众号“回到2049”。",
  "have_more_intro": false,
  "time_until_now": "1月前",
  "category_name": null,
  "category_title": null,
  "played_secs": null,
  "is_paid": false,
  "is_free": false,
  "price": null,
  "discounted_price": null
}