{
  "id": 203019393,
  "play_path_64": "http://audio.cos.xmcdn.com/group62/M0A/74/A3/wKgMcV1IJ0KQk4NcADugn0_9Pi4526.m4a",
  "play_path_32": "http://audio.cos.xmcdn.com/group62/M0A/74/9F/wKgMcV1IJzmDB69QABbO7xybkoY716.m4a",
  "play_path": "http://audio.cos.xmcdn.com/group62/M0A/74/A3/wKgMcV1IJ0KQk4NcADugn0_9Pi4526.m4a",
  "duration": 482,
  "title": "无人驾驶的几点不成熟思考（下）",
  "nickname": null,
  "uid": 43396178,
  "waveform": "group62/M0A/74/C2/wKgMZ11IJ0qhREvCAAAKHVdLN3Y8970.js",
  "upload_id": "u_223256922",
  "cover_url": "https://imagev2.xmcdn.com/group63/M0B/76/5B/wKgMcl1IJzPjfhTYAAILHRjNvXU269.jpg!op_type=5&upload_type=album&device_type=ios&name=web_large&strip=0&quality=7",
  "cover_url_142": "https://imagev2.xmcdn.com/group63/M0B/76/5B/wKgMcl1IJzPjfhTYAAILHRjNvXU269.jpg!op_type=5&upload_type=album&device_type=ios&name=web_large&strip=0&quality=7",
  "formatted_created_at": "2019-08-06 00:01:00",
  "is_favorited": false,
  "play_count": 27734,
  "comments_count": 42,
  "shares_count": 18,
  "favorites_count": 82,
  "album_id": 4310827,
  "album_title": "回到2049",
  "intro": "无人驾驶汽车发展过程中，可能面临哪些阻碍？\r\n\r\n\r\n \r\n  \r\n \r\n \r\n \r\n 节目文本、视频，及更多精神与物质上的享受，尽在公众号“回到2049”。",
  "have_more_intro": false,
  "time_until_now": "9月前",
  "category_name": null,
  "category_title": null,
  "played_secs": null,
  "is_paid": false,
  "is_free": false,
  "price": null,
  "discounted_price": null
}