{
  "id": 252482880,
  "play_path_64": "http://aod.cos.tx.xmcdn.com/group71/M0B/67/7C/wKgOz15BazzRX80TALkVnb1_ssY442.m4a",
  "play_path_32": "http://aod.cos.tx.xmcdn.com/group71/M0B/67/53/wKgO2V5BazXhYUTNAEf8Xe0askc043.m4a",
  "play_path": "http://aod.cos.tx.xmcdn.com/group71/M0B/67/7C/wKgOz15BazzRX80TALkVnb1_ssY442.m4a",
  "duration": 1482,
  "title": "爱因斯坦的100亿年",
  "nickname": null,
  "uid": 21189289,
  "waveform": "group71/M0B/67/70/wKgOz15Bax2zx_6zAAAKrdQ9HXE9791.js",
  "upload_id": "u_6070348140",
  "cover_url": "https://imagev2.xmcdn.com/group55/M01/91/3C/wKgLdVxw7KTgn7vcAAFf2rzyUUA124.jpg!op_type=5&upload_type=album&device_type=ios&name=web_large&strip=0&quality=7",
  "cover_url_142": "https://imagev2.xmcdn.com/group55/M01/91/3C/wKgLdVxw7KTgn7vcAAFf2rzyUUA124.jpg!op_type=5&upload_type=album&device_type=ios&name=web_large&strip=0&quality=7",
  "formatted_created_at": "2020-02-10 22:39:00",
  "is_favorited": false,
  "play_count": 10319,
  "comments_count": 44,
  "shares_count": 8,
  "favorites_count": 43,
  "album_id": 21469108,
  "album_title": "科学星球",
  "intro": "这一期咱们继续说故事，这个故事算是半个原创，改编自阿西莫夫的《最后的问题》，算是我个人喜欢的科幻故事的TOP10以内。听到结尾，或许你能感受到当年我读它时候的震撼。",
  "have_more_intro": false,
  "time_until_now": "3月前",
  "category_name": null,
  "category_title": null,
  "played_secs": null,
  "is_paid": false,
  "is_free": false,
  "price": null,
  "discounted_price": null
}