{"id":46104907,"play_path_64":"http://aod.cos.tx.xmcdn.com/group30/M06/66/FD/wKgJXlmC5YrTlzUFAJqURYGLm_c816.m4a","play_path_32":"http://aod.cos.tx.xmcdn.com/group30/M0B/66/FF/wKgJXlmC5Y3AB9CeADsB6HPLaOs306.m4a","play_path":"http://aod.cos.tx.xmcdn.com/group30/M06/66/FD/wKgJXlmC5YrTlzUFAJqURYGLm_c816.m4a","duration":1252,"title":"《双学济南话》郭德纲 王文林","nickname":null,"uid":1000202,"waveform":"group31/M05/35/03/wKgJSVmC3BzQ_9epAAAJqD7-PCE7323.js","upload_id":"c_807598","cover_url":"https://imagev2.xmcdn.com/group31/M07/21/18/wKgJSVmBi5GwDYaxAAA1jHU5vC4048.jpg!op_type=5&upload_type=album&device_type=ios&name=web_large&strip=0&quality=7","cover_url_142":"https://imagev2.xmcdn.com/group31/M07/21/18/wKgJSVmBi5GwDYaxAAA1jHU5vC4048.jpg!op_type=5&upload_type=album&device_type=ios&name=web_large&strip=0&quality=7","formatted_created_at":"2017-08-03 16:57:00","is_favorited":false,"play_count":3416083,"comments_count":152,"shares_count":363,"favorites_count":3171,"album_id":9742774,"album_title":"郭德纲相声经典","intro":"","have_more_intro":false,"time_until_now":"2年前","category_name":null,"category_title":null,"played_secs":null,"is_paid":false,"is_free":false,"price":null,"discounted_price":null}