{
  "id": 10738648,
  "play_path_64": "http://audio.cos.xmcdn.com/group9/M01/CA/2D/wKgDZlZsiDaBV1klALtX5au9rTo005.m4a",
  "play_path_32": "http://audio.cos.xmcdn.com/group14/M03/CA/69/wKgDZFZsiB2QprRPAEeDj-kLOY4007.m4a",
  "play_path": "http://audio.cos.xmcdn.com/group9/M01/CA/2D/wKgDZlZsiDaBV1klALtX5au9rTo005.m4a",
  "duration": 1518,
  "title": "前传：02.彩色火焰",
  "nickname": null,
  "uid": 10946830,
  "waveform": "group14/M03/CA/A5/wKgDY1ZsiCPQyv4uAAAKu3xpn2k7335.js",
  "upload_id": "u_9495206",
  "cover_url": "https://imagev2.xmcdn.com/group15/M0B/C9/18/wKgDaFZsh7jzkxu2AACp6Q2ipKE864.jpg!op_type=5&upload_type=album&device_type=ios&name=web_large&strip=0&quality=7",
  "cover_url_142": "https://imagev2.xmcdn.com/group15/M0B/C9/18/wKgDaFZsh7jzkxu2AACp6Q2ipKE864.jpg!op_type=5&upload_type=album&device_type=ios&name=web_large&strip=0&quality=7",
  "formatted_created_at": "2015-12-13 04:48:00",
  "is_favorited": false,
  "play_count": 235364,
  "comments_count": 192,
  "shares_count": 302,
  "favorites_count": 791,
  "album_id": 3308560,
  "album_title": "量子力学外传",
  "intro": "",
  "have_more_intro": false,
  "time_until_now": "4年前",
  "category_name": null,
  "category_title": null,
  "played_secs": null,
  "is_paid": false,
  "is_free": false,
  "price": null,
  "discounted_price": null
}