{
  "id": 32370435,
  "play_path_64": "http://audio.cos.xmcdn.com/group18/M09/C3/E4/wKgJKljDxzbyz0rJAjv_IMAmKns492.m4a",
  "play_path_32": "http://audio.cos.xmcdn.com/group25/M09/EA/6B/wKgJNljDxxbCmao1ANqxb6b8yS4912.m4a",
  "play_path": "http://audio.cos.xmcdn.com/group18/M09/C3/E4/wKgJKljDxzbyz0rJAjv_IMAmKns492.m4a",
  "duration": 4630,
  "title": "367老美的御林军【海豹突击队、三角洲部队等等】",
  "nickname": null,
  "uid": 32231821,
  "waveform": "group18/M09/C4/76/wKgJJVjDxzbgCFoGAAAKyV143Ws6283.js",
  "upload_id": "u_33034526",
  "cover_url": "https://imagev2.xmcdn.com/group25/M05/EA/27/wKgJNljDvc-Bf5ygAADfTUi9i9c171.jpg!op_type=5&upload_type=album&device_type=ios&name=web_large&strip=0&quality=7",
  "cover_url_142": "https://imagev2.xmcdn.com/group25/M05/EA/27/wKgJNljDvc-Bf5ygAADfTUi9i9c171.jpg!op_type=5&upload_type=album&device_type=ios&name=web_large&strip=0&quality=7",
  "formatted_created_at": "2017-03-11 17:43:00",
  "is_favorited": false,
  "play_count": 15588,
  "comments_count": 26,
  "shares_count": 7,
  "favorites_count": 69,
  "album_id": 4769101,
  "album_title": "思考盒子",
  "intro": "【兵临城下】",
  "have_more_intro": false,
  "time_until_now": "3年前",
  "category_name": null,
  "category_title": null,
  "played_secs": null,
  "is_paid": false,
  "is_free": false,
  "price": null,
  "discounted_price": null
}