{
  "id": 146380165,
  "play_path_64": "http://aod.cos.tx.xmcdn.com/group54/M07/8A/1E/wKgLfVwboh3w2TaIAP4DL-IxtMU167.m4a",
  "play_path_32": "http://aod.cos.tx.xmcdn.com/group52/M01/8B/D2/wKgLcFwbqYiAiBJ1AGEfY16sXyE039.m4a",
  "play_path": "http://aod.cos.tx.xmcdn.com/group54/M07/8A/1E/wKgLfVwboh3w2TaIAP4DL-IxtMU167.m4a",
  "duration": 2056,
  "title": "S03E51基因编辑之伦理沉思",
  "nickname": null,
  "uid": 43396178,
  "waveform": "group52/M0A/8A/64/wKgLcFwboj2xbvLxAAAMTyRfqcE6887.js",
  "upload_id": "u_156498125",
  "cover_url": "https://imagev2.xmcdn.com/group52/M06/8A/12/wKgLcFwboMqi_MWFAABPQrhZ9IY675.jpg!op_type=5&upload_type=album&device_type=ios&name=web_large&strip=0&quality=7",
  "cover_url_142": "https://imagev2.xmcdn.com/group52/M06/8A/12/wKgLcFwboMqi_MWFAABPQrhZ9IY675.jpg!op_type=5&upload_type=album&device_type=ios&name=web_large&strip=0&quality=7",
  "formatted_created_at": "2018-12-21 00:02:00",
  "is_favorited": false,
  "play_count": 36211,
  "comments_count": 112,
  "shares_count": 63,
  "favorites_count": 188,
  "album_id": 4310827,
  "album_title": "回到2049",
  "intro": "基因编辑与人类改造在伦理层面的胡乱思索。\r\n\r\n\r\n \r\n  \r\n \r\n \r\n \r\n 节目文本、视频，及更多精神与物质上的享受，尽在微信公众号“回到2049”。",
  "have_more_intro": false,
  "time_until_now": "1年前",
  "category_name": null,
  "category_title": null,
  "played_secs": null,
  "is_paid": false,
  "is_free": false,
  "price": null,
  "discounted_price": null
}