{
  "id": 144627830,
  "play_path_64": "http://audio.cos.xmcdn.com/group52/M0A/BE/C9/wKgLcFwTPiXBZda5AVK32JV3C5A299.m4a",
  "play_path_32": "http://audio.cos.xmcdn.com/group54/M01/BE/01/wKgLclwTPV7h11wHAIGCdCLoDBs788.m4a",
  "play_path": "http://audio.cos.xmcdn.com/group52/M0A/BE/C9/wKgLcFwTPiXBZda5AVK32JV3C5A299.m4a",
  "duration": 2742,
  "title": "234：比黄金还贵的“铝”？",
  "nickname": null,
  "uid": 7200706,
  "waveform": "group53/M02/BE/B0/wKgLcVwTPb3h5gUsAAAKyUoE_QY9191.js",
  "upload_id": "u_153211969",
  "cover_url": "https://imagev2.xmcdn.com/group13/M09/37/1E/wKgDXVWWXQ2D0qUfAAM0Is5jf_s669.jpg!op_type=5&upload_type=album&device_type=ios&name=web_large&strip=0&quality=7",
  "cover_url_142": "https://imagev2.xmcdn.com/group13/M09/37/1E/wKgDXVWWXQ2D0qUfAAM0Is5jf_s669.jpg!op_type=5&upload_type=album&device_type=ios&name=web_large&strip=0&quality=7",
  "formatted_created_at": "2018-12-14 18:00:00",
  "is_favorited": false,
  "play_count": 1122824,
  "comments_count": 576,
  "shares_count": 118,
  "favorites_count": 544,
  "album_id": 246622,
  "album_title": "原来是这样？！",
  "intro": "你知道吗：如今随处可见、唾手可得的铝，曾经也高贵过——贵妇们拿它当首饰，国王用来做皇冠。可为什么地壳中含量最高的金属元素一度会如此稀有？古人利用汞镀金的方法，又和单质铝的获得有怎样的关系？通过“铝”走下神坛的故事，听听科学探索之路，顺便想想如今的黄金与钻石吧~",
  "have_more_intro": false,
  "time_until_now": "1年前",
  "category_name": null,
  "category_title": null,
  "played_secs": null,
  "is_paid": false,
  "is_free": false,
  "price": null,
  "discounted_price": null
}