{
  "id": 23712774,
  "play_path_64": "http://aod.cos.tx.xmcdn.com/group20/M07/9A/FA/wKgJLFgLQUnBpKb7AR3dNI2fIsU486.m4a",
  "play_path_32": "http://aod.cos.tx.xmcdn.com/group18/M0A/9C/04/wKgJJVgLQS3xRrIxAG1M3WUYPb4222.m4a",
  "play_path": "http://aod.cos.tx.xmcdn.com/group20/M07/9A/FA/wKgJLFgLQUnBpKb7AR3dNI2fIsU486.m4a",
  "duration": 2314,
  "title": "149怎么才能获得【普利策奖 】",
  "nickname": null,
  "uid": 32231821,
  "waveform": "group17/M02/9D/29/wKgJKVgLQT-BY-4QAAAKy1tK9vs7206.js",
  "upload_id": "u_23791153",
  "cover_url": "https://imagev2.xmcdn.com/group20/M08/9A/F0/wKgJLFgLPn7C1vLGAAEAZ6XoHnw451.jpg!op_type=5&upload_type=album&device_type=ios&name=web_large&strip=0&quality=7",
  "cover_url_142": "https://imagev2.xmcdn.com/group20/M08/9A/F0/wKgJLFgLPn7C1vLGAAEAZ6XoHnw451.jpg!op_type=5&upload_type=album&device_type=ios&name=web_large&strip=0&quality=7",
  "formatted_created_at": "2016-10-22 18:35:00",
  "is_favorited": false,
  "play_count": 9718,
  "comments_count": 26,
  "shares_count": 3,
  "favorites_count": 39,
  "album_id": 4769101,
  "album_title": "思考盒子",
  "intro": "普利策奖",
  "have_more_intro": false,
  "time_until_now": "3年前",
  "category_name": null,
  "category_title": null,
  "played_secs": null,
  "is_paid": false,
  "is_free": false,
  "price": null,
  "discounted_price": null
}