{
  "id": 17545131,
  "play_path_64": "http://audio.cos.xmcdn.com/group13/M00/9E/51/wKgDXVdurKKx65cCADchm-OPdVE586.m4a",
  "play_path_32": "http://audio.cos.xmcdn.com/group5/M06/90/77/wKgDtldur--iaxowABUW95WNd1w477.m4a",
  "play_path": "http://audio.cos.xmcdn.com/group13/M00/9E/51/wKgDXVdurKKx65cCADchm-OPdVE586.m4a",
  "duration": 446,
  "title": "宇宙微波背景辐射",
  "nickname": null,
  "uid": 43396178,
  "waveform": "group11/M04/A8/C7/wKgDbVdurLHDuzRHAAALOM7lcCw1221.js",
  "upload_id": "u_16539923",
  "cover_url": "https://imagev2.xmcdn.com/group16/M07/9D/E0/wKgDaldurEjRduWNAAE7WcNs5fo938.jpg!op_type=5&upload_type=album&device_type=ios&name=web_large&strip=0&quality=7",
  "cover_url_142": "https://imagev2.xmcdn.com/group16/M07/9D/E0/wKgDaldurEjRduWNAAE7WcNs5fo938.jpg!op_type=5&upload_type=album&device_type=ios&name=web_large&strip=0&quality=7",
  "formatted_created_at": "2016-06-26 00:09:00",
  "is_favorited": false,
  "play_count": 44845,
  "comments_count": 11,
  "shares_count": 12,
  "favorites_count": 65,
  "album_id": 4310827,
  "album_title": "回到2049",
  "intro": "宇宙初生的第一张照片，穿越140亿年的回响。",
  "have_more_intro": false,
  "time_until_now": "3年前",
  "category_name": null,
  "category_title": null,
  "played_secs": null,
  "is_paid": false,
  "is_free": false,
  "price": null,
  "discounted_price": null
}