{
  "id": 244340505,
  "play_path_64": "http://aod.cos.tx.xmcdn.com/group71/M03/CB/F8/wKgOz14fN8vzZTCeAEyzscbcJ0w521.m4a",
  "play_path_32": "http://aod.cos.tx.xmcdn.com/group70/M04/CD/23/wKgOzl4fN6CCFIdrAB3Yd4AqN94930.m4a",
  "play_path": "http://aod.cos.tx.xmcdn.com/group71/M03/CB/F8/wKgOz14fN8vzZTCeAEyzscbcJ0w521.m4a",
  "duration": 614,
  "title": "照亮文明之火：无奈之举",
  "nickname": null,
  "uid": 43396178,
  "waveform": "group72/M03/86/6A/wKgO0F4fN4ihLAzlAAAKM2I3-nw4997.js",
  "upload_id": "u_6026291240",
  "cover_url": "https://imagev2.xmcdn.com/group71/M03/C8/E5/wKgO2V4fGmiizvmqAAJmh1oCGsQ106.jpg!op_type=5&upload_type=album&device_type=ios&name=web_large&strip=0&quality=7",
  "cover_url_142": "https://imagev2.xmcdn.com/group71/M03/C8/E5/wKgO2V4fGmiizvmqAAJmh1oCGsQ106.jpg!op_type=5&upload_type=album&device_type=ios&name=web_large&strip=0&quality=7",
  "formatted_created_at": "2020-01-16 00:01:00",
  "is_favorited": false,
  "play_count": 19574,
  "comments_count": 25,
  "shares_count": 2,
  "favorites_count": 70,
  "album_id": 4310827,
  "album_title": "回到2049",
  "intro": "火怎样走进了原始人的生活之中？今日奖品：iPhone11 Pro、深空灰色、128G，￥8.88，感谢老板新年投食，祝愿老板新年发大财、行大运！\r\n\r\n\r\n  \r\n\r\n\r\n \r\n \r\n 节目文本、视频，及更多精神与物质上的享受，尽在公众号“回到2049”。",
  "have_more_intro": false,
  "time_until_now": "3月前",
  "category_name": null,
  "category_title": null,
  "played_secs": null,
  "is_paid": false,
  "is_free": false,
  "price": null,
  "discounted_price": null
}