{
  "id": 51355431,
  "play_path_64": "http://aod.cos.tx.xmcdn.com/group32/M03/D3/89/wKgJS1m_4m-DUVQqAFBEPWLoOU0642.m4a",
  "play_path_32": "http://aod.cos.tx.xmcdn.com/group33/M09/D5/23/wKgJnVm_7SmRJoqQAB6zKU6hU-Y233.m4a",
  "play_path": "http://aod.cos.tx.xmcdn.com/group32/M03/D3/89/wKgJS1m_4m-DUVQqAFBEPWLoOU0642.m4a",
  "duration": 649,
  "title": "灵异现象：幽灵显形与心灵感应",
  "nickname": null,
  "uid": 43396178,
  "waveform": "group32/M03/D3/8F/wKgJS1m_4oeAqOlEAAALKpcayC09929.js",
  "upload_id": "u_52899129",
  "cover_url": "https://imagev2.xmcdn.com/group31/M02/EB/9B/wKgJSVm_4hfCY_2bAAFfU1ijOQw220.jpg!op_type=5&upload_type=album&device_type=ios&name=web_large&strip=0&quality=7",
  "cover_url_142": "https://imagev2.xmcdn.com/group31/M02/EB/9B/wKgJSVm_4hfCY_2bAAFfU1ijOQw220.jpg!op_type=5&upload_type=album&device_type=ios&name=web_large&strip=0&quality=7",
  "formatted_created_at": "2017-09-19 00:01:00",
  "is_favorited": false,
  "play_count": 33173,
  "comments_count": 52,
  "shares_count": 15,
  "favorites_count": 78,
  "album_id": 4310827,
  "album_title": "回到2049",
  "intro": "幽灵为什么会显形？心灵感应真的存在吗？",
  "have_more_intro": false,
  "time_until_now": "2年前",
  "category_name": null,
  "category_title": null,
  "played_secs": null,
  "is_paid": false,
  "is_free": false,
  "price": null,
  "discounted_price": null
}