{
  "id": 39439032,
  "play_path_64": "http://aod.cos.tx.xmcdn.com/group28/M02/0A/4D/wKgJXFkulQ3zFaC5ADyRffFe0B4718.m4a",
  "play_path_32": "http://aod.cos.tx.xmcdn.com/group28/M07/08/F4/wKgJSFkulQSQh6vkABcrKCOEBTQ436.m4a",
  "play_path": "http://aod.cos.tx.xmcdn.com/group28/M02/0A/4D/wKgJXFkulQ3zFaC5ADyRffFe0B4718.m4a",
  "duration": 490,
  "title": "【量子世界】海森堡不确定性原理",
  "nickname": null,
  "uid": 43396178,
  "waveform": "group28/M07/08/F5/wKgJSFkulRCBtAU3AAAKyGk08fg6514.js",
  "upload_id": "u_40360419",
  "cover_url": "https://imagev2.xmcdn.com/group28/M00/0A/3C/wKgJXFkulHnjSbEwAAEnneTsZ4Q751.png!op_type=5&upload_type=album&device_type=ios&name=web_large&strip=0&quality=7",
  "cover_url_142": "https://imagev2.xmcdn.com/group28/M00/0A/3C/wKgJXFkulHnjSbEwAAEnneTsZ4Q751.png!op_type=5&upload_type=album&device_type=ios&name=web_large&strip=0&quality=7",
  "formatted_created_at": "2017-06-01 00:01:00",
  "is_favorited": false,
  "play_count": 24533,
  "comments_count": 20,
  "shares_count": 11,
  "favorites_count": 61,
  "album_id": 4310827,
  "album_title": "回到2049",
  "intro": "为什么粒子的位置与速度无法准确测量，这一无法逾越的极限又意味着什么？",
  "have_more_intro": false,
  "time_until_now": "2年前",
  "category_name": null,
  "category_title": null,
  "played_secs": null,
  "is_paid": false,
  "is_free": false,
  "price": null,
  "discounted_price": null
}